{
  "_format": "hh-sol-cache-2",
  "files": {
    "/home/emma-ido/Solidity/Hardhat/contracts/MyTest.sol": {
      "lastModificationDate": 1693073545277,
      "contentHash": "94bc1a39e743448ccb2f78c82365746f",
      "sourceName": "contracts/MyTest.sol",
      "solcConfig": {
        "version": "0.8.19",
        "settings": {
          "optimizer": {
            "enabled": false,
            "runs": 200
          },
          "outputSelection": {
            "*": {
              "*": [
                "abi",
                "evm.bytecode",
                "evm.deployedBytecode",
                "evm.methodIdentifiers",
                "metadata"
              ],
              "": [
                "ast"
              ]
            }
          }
        }
      },
      "imports": [
        "hardhat/console.sol"
      ],
      "versionPragmas": [
        "^0.8.9"
      ],
      "artifacts": [
        "MyTest"
      ]
    },
    "/home/emma-ido/Solidity/Hardhat/node_modules/hardhat/console.sol": {
      "lastModificationDate": 1693071989487,
      "contentHash": "896f68942c3a20e9ae3c3c5bfd3add54",
      "sourceName": "hardhat/console.sol",
      "solcConfig": {
        "version": "0.8.19",
        "settings": {
          "optimizer": {
            "enabled": false,
            "runs": 200
          },
          "outputSelection": {
            "*": {
              "*": [
                "abi",
                "evm.bytecode",
                "evm.deployedBytecode",
                "evm.methodIdentifiers",
                "metadata"
              ],
              "": [
                "ast"
              ]
            }
          }
        }
      },
      "imports": [],
      "versionPragmas": [
        ">=0.4.22 <0.9.0"
      ],
      "artifacts": [
        "console"
      ]
    }
  }
}
